README.rst
setup.py
aio_pybars/__init__.py
aio_pybars/loader.py
aio_pybars/render.py
aio_pybars.egg-info/PKG-INFO
aio_pybars.egg-info/SOURCES.txt
aio_pybars.egg-info/dependency_links.txt
aio_pybars.egg-info/requires.txt
aio_pybars.egg-info/top_level.txt