Metadata-Version: 1.1
Name: aio-pybars
Version: 0.1.0
Summary: pybars3 (handlebars) templates rendering for aiohttp.
Home-page: https://github.com/rrader/aio_pybars
Author: Roman Rader
Author-email: antigluk@gmail.com
License: BSD
Platform: POSIX
Classifier: License :: OSI Approved :: BSD License
Classifier: Intended Audience :: Developers
Classifier: Programming Language :: Python :: 3
Classifier: Programming Language :: Python :: 3.3
Classifier: Programming Language :: Python :: 3.4
Classifier: Programming Language :: Python :: 3.5
Classifier: Environment :: Web Environment
Classifier: Development Status :: 4 - Beta
